neutron_taas/__init__.py
neutron_taas/_i18n.py
neutron_taas/opts.py
neutron_taas/common/__init__.py
neutron_taas/common/config.py
neutron_taas/common/constants.py
neutron_taas/common/topics.py
neutron_taas/common/utils.py
neutron_taas/db/__init__.py
neutron_taas/db/head.py
neutron_taas/db/taas_db.py
neutron_taas/db/tap_mirror_db.py
neutron_taas/db/migration/__init__.py
neutron_taas/db/migration/taas_init_ops.py
neutron_taas/db/migration/alembic_migration/README
neutron_taas/db/migration/alembic_migration/__init__.py
neutron_taas/db/migration/alembic_migration/env.py
neutron_taas/db/migration/alembic_migration/script.py.mako
neutron_taas/db/migration/alembic_migration/versions/CONTRACT_HEAD
neutron_taas/db/migration/alembic_migration/versions/EXPAND_HEAD
neutron_taas/db/migration/alembic_migration/versions/start_neutron_taas.py
neutron_taas/db/migration/alembic_migration/versions/2025.1/expand/f8f1f10ebaf9_mirroring_for_taas.py
neutron_taas/db/migration/alembic_migration/versions/newton/contract/1817af933379_remove_network_id_from_tap_service.py
neutron_taas/db/migration/alembic_migration/versions/newton/contract/2ecce0368a62_add_foreign_key_constraint_on_tap_id_association.py
neutron_taas/db/migration/alembic_migration/versions/newton/contract/4086b3cffc01_rename_tenant_to_project.py
neutron_taas/db/migration/alembic_migration/versions/newton/contract/80c85b675b6e_initial_newton_no_op_contract_script.py
neutron_taas/db/migration/alembic_migration/versions/newton/expand/04625466c6fa_initial_newton_no_op_expand_script.py
neutron_taas/db/migration/alembic_migration/versions/newton/expand/fddbdec8711a_add_status.py
neutron_taas/db/migration/alembic_migration/versions/pike/contract/bac61f603e39_alter_tap_id_associations_to_support_tap_id_reuse.py
neutron_taas/db/migration/alembic_migration/versions/stein/expand/ccbcc559d175_add_vlan_filter_to_tap_flow.py
neutron_taas/extensions/__init__.py
neutron_taas/extensions/taas.py
neutron_taas/extensions/tap_mirror.py
tap_as_a_service-16.0.0.dist-info/AUTHORS
tap_as_a_service-16.0.0.dist-info/LICENSE
tap_as_a_service-16.0.0.dist-info/METADATA
tap_as_a_service-16.0.0.dist-info/WHEEL
tap_as_a_service-16.0.0.dist-info/entry_points.txt
tap_as_a_service-16.0.0.dist-info/pbr.json
tap_as_a_service-16.0.0.dist-info/top_level.txt
tap_as_a_service-16.0.0.dist-info/RECORD
