Metadata-Version: 2.1
Name: tap-as-a-service
Version: 16.0.0
Summary: Tap-as-a-Service (TaaS) is an extension to the OpenStack network service (Neutron), it provides remote port mirroring capability for tenant virtual networks.
Home-page: http://www.openstack.org/
Author: OpenStack
Author-email: openstack-discuss@lists.openstack.org
Classifier: Environment :: OpenStack
Classifier: Intended Audience :: Information Technology
Classifier: Intended Audience :: System Administrators
Classifier: License :: OSI Approved :: Apache Software License
Classifier: Operating System :: POSIX :: Linux
Classifier: Programming Language :: Python
Classifier: Programming Language :: Python :: 3
Classifier: Programming Language :: Python :: 3.10
Classifier: Programming Language :: Python :: 3.11
Classifier: Programming Language :: Python :: 3.12
Requires-Python: >=3.10
License-File: LICENSE
License-File: AUTHORS
Requires-Dist: pbr>=5.5.0
Requires-Dist: neutron>=16.0.0.0b1
Requires-Dist: neutron-lib>=2.11.0
Requires-Dist: openstacksdk>=0.102.0
Requires-Dist: python-openstackclient>=3.12.0
Requires-Dist: osc-lib>=2.3.0
